lovekit/__init__.py
lovekit/arkitekt.py
lovekit/errors.py
lovekit/file.py
lovekit/funcs.py
lovekit/lovekit.py
lovekit/py.typed
lovekit/rath.py
lovekit/rekuest.py
lovekit/api/project.json
lovekit/api/schema.graphql
lovekit/api/schema.py
lovekit-1.1.0.dist-info/METADATA
lovekit-1.1.0.dist-info/WHEEL
lovekit-1.1.0.dist-info/RECORD
