Metadata-Version: 2.4
Name: lovekit
Version: 1.1.0
Author-email: jhnnsrs <jhnnsrs@gmail.com>
Requires-Python: >=3.11
Requires-Dist: aiohttp<4,>=3.9.5
Requires-Dist: livekit>=0.16.3
Requires-Dist: rath>=3.5
